reckon/__about__.py
reckon/__init__.py
reckon/glob.py
reckon/loc.py
reckon/protos.py
reckon/util.py
reckon-0.2.0.dist-info/LICENSE
reckon-0.2.0.dist-info/METADATA
reckon-0.2.0.dist-info/WHEEL
reckon-0.2.0.dist-info/top_level.txt
reckon-0.2.0.dist-info/RECORD
